orwynn_rbac/__init__.py
orwynn_rbac/bootscripts.py
orwynn_rbac/constants.py
orwynn_rbac/controllers.py
orwynn_rbac/documents.py
orwynn_rbac/dtos.py
orwynn_rbac/enums.py
orwynn_rbac/errors.py
orwynn_rbac/models.py
orwynn_rbac/search.py
orwynn_rbac/services.py
orwynn_rbac/test_controllers.py
orwynn_rbac/test_services.py
orwynn_rbac/testing.py
orwynn_rbac/types.py
orwynn_rbac/utils.py
orwynn_rbac-0.1.4.dist-info/LICENSE
orwynn_rbac-0.1.4.dist-info/METADATA
orwynn_rbac-0.1.4.dist-info/WHEEL
orwynn_rbac-0.1.4.dist-info/RECORD
