Metadata-Version: 2.1
Name: orwynn-rbac
Version: 0.1.4
Summary: 👮 Role-Based-Access-Control module for Orwynn framework
Home-page: https://github.com/slimebones/orwynn_rbac
Keywords: framework,rbac,role-based-access-control,role,permission
Author: ryzhovalex
Author-email: thed4rkof@gmail.com
Requires-Python: >=3.11,<4.0
Classifier: Programming Language :: Python :: 3
Classifier: Programming Language :: Python :: 3.11
Requires-Dist: orwynn (>=1.4.0,<2.0.0)
Project-URL: Documentation, https://github.com/slimebones/orwynn_rbac
Project-URL: Repository, https://github.com/slimebones/orwynn_rbac
